pytap2/__init__.py
pytap2/py.typed
pytap2-2.3.0.dist-info/LICENSE.txt
pytap2-2.3.0.dist-info/METADATA
pytap2-2.3.0.dist-info/WHEEL
pytap2-2.3.0.dist-info/top_level.txt
pytap2-2.3.0.dist-info/RECORD
