Metadata-Version: 2.1
Name: pytap2
Version: 2.3.0
Summary: Object-oriented wrapper around the Linux Tun/Tap device
Home-page: https://github.com/johnthagen/pytap2
Author: John Hagen
Author-email: johnthagen@gmail.com
License: MIT
Keywords: pytap,tun,tap,networking
Classifier: Development Status :: 4 - Beta
Classifier: Intended Audience :: Developers
Classifier: License :: OSI Approved :: MIT License
Classifier: Operating System :: POSIX :: Linux
Classifier: Programming Language :: Python
Classifier: Programming Language :: Python :: 3
Classifier: Programming Language :: Python :: 3 :: Only
Classifier: Programming Language :: Python :: 3.8
Classifier: Programming Language :: Python :: 3.9
Classifier: Programming Language :: Python :: 3.10
Classifier: Programming Language :: Python :: 3.11
Classifier: Topic :: Software Development :: Libraries :: Python Modules
Requires-Python: >=3.8
License-File: LICENSE.txt
